fs2f/__init__.py
fs2f/fs2f.py
fs2f-0.0.1.241223.dist-info/LICENSE.txt
fs2f-0.0.1.241223.dist-info/WHEEL
fs2f-0.0.1.241223.dist-info/METADATA
fs2f-0.0.1.241223.dist-info/RECORD
