Metadata-Version: 2.3
Name: fs2f
Version: 0.0.1.241223
Summary: fs2f: A tool for taking snapshots of a file structure into a single file.
Home-page: https://github.com/codyverse/fs2f
License: MIT
Keywords: file, snapshot, image, archive
Author: Andrii Burkatskyi aka andr11b
Author-email: 4ndr116@gmail.com
Requires-Python: >=3.8
Requires-Dist: pytest>=6.0 ; extra == "dev"
Provides-Extra: dev
